CHANGES.txt
LICENSE.txt
MANIFEST.in
README.txt
buildout.cfg
setup.py
src/m01/__init__.py
src/m01.grid.egg-info/PKG-INFO
src/m01.grid.egg-info/SOURCES.txt
src/m01.grid.egg-info/dependency_links.txt
src/m01.grid.egg-info/namespace_packages.txt
src/m01.grid.egg-info/not-zip-safe
src/m01.grid.egg-info/requires.txt
src/m01.grid.egg-info/top_level.txt
src/m01/grid/README.txt
src/m01/grid/__init__.py
src/m01/grid/base.py
src/m01/grid/browser.py
src/m01/grid/browser.zcml
src/m01/grid/chunker.py
src/m01/grid/configure.zcml
src/m01/grid/exceptions.py
src/m01/grid/gridfs.txt
src/m01/grid/interfaces.py
src/m01/grid/item.py
src/m01/grid/layer.py
src/m01/grid/schema.py
src/m01/grid/tests.py
src/m01/grid/traverser.py
src/m01/grid/testing/__init__.py
src/m01/grid/testing/sandbox/LICENSE-Community.txt
src/m01/grid/widget/__init__.py
src/m01/grid/widget/configure.zcml
src/m01/grid/widget/converter.py
src/m01/grid/widget/error.py
src/m01/grid/widget/widget_display.pt
src/m01/grid/widget/widget_input.pt